[{"Lean":{"X":0.119200774,"Y":0.241976619},"Activities":{"EyeLeftClosed":0,"EyeRightClosed":0,"MouthOpen":0,"MouthMoved":0,"LookingAway":0},"Appearance":{"WearingGlasses":0},"ClippedEdges":0,"Engaged":0,"Expressions":{"Neutral":0,"Happy":0},"HandLeftConfidence":1,"HandLeftState":3,"HandRightConfidence":0,"HandRightState":0,"IsRestricted":false,"IsTracked":true,"JointOrientations":{"SpineBase":{"JointType":0,"Orientation":{"X":-0.0123952748,"Y":0.993432462,"Z":-0.03573862,"W":0.107986562}},"SpineMid":{"JointType":1,"Orientation":{"X":-0.0165020172,"Y":0.973906338,"Z":-0.03403785,"W":0.223775625}},"Neck":{"JointType":2,"Orientation":{"X":-0.0320243649,"Y":0.933302939,"Z":-0.06556109,"W":0.351599038}},"Head":{"JointType":3,"Orientation":{"X":0.0,"Y":0.0,"Z":0.0,"W":0.0}},"ShoulderLeft":{"JointType":4,"Orientation":{"X":0.7819044,"Y":-0.477771372,"Z":0.33392325,"W":-0.221032456}},"ElbowLeft":{"JointType":5,"Orientation":{"X":0.8302978,"Y":0.175354764,"Z":0.0289926287,"W":-0.528219342}},"WristLeft":{"JointType":6,"Orientation":{"X":-0.552072346,"Y":-0.0868897662,"Z":-0.5347815,"W":0.633778453}},"HandLeft":{"JointType":7,"Orientation":{"X":-0.5253407,"Y":-0.139023051,"Z":-0.579633057,"W":0.6072192}},"ShoulderRight":{"JointType":8,"Orientation":{"X":0.817491531,"Y":0.468768179,"Z":0.271031857,"W":0.196228415}},"ElbowRight":{"JointType":9,"Orientation":{"X":0.4927852,"Y":0.5421882,"Z":0.5845003,"W":0.3486461}},"WristRight":{"JointType":10,"Orientation":{"X":-0.288624972,"Y":0.45384112,"Z":0.791831,"W":-0.289357066}},"HandRight":{"JointType":11,"Orientation":{"X":-0.246018469,"Y":0.369988352,"Z":0.824795365,"W":-0.349708557}},"HipLeft":{"JointType":12,"Orientation":{"X":0.6729063,"Y":-0.6530148,"Z":0.265500635,"W":-0.224228233}},"KneeLeft":{"JointType":13,"Orientation":{"X":0.776172936,"Y":-0.03548325,"Z":-0.625051737,"W":0.0748786554}},"AnkleLeft":{"JointType":14,"Orientation":{"X":0.7416614,"Y":-0.09163531,"Z":-0.6516868,"W":0.129790917}},"FootLeft":{"JointType":15,"Orientation":{"X":0.0,"Y":0.0,"Z":0.0,"W":0.0}},"HipRight":{"JointType":16,"Orientation":{"X":0.6954648,"Y":0.692713857,"Z":-0.159464359,"W":-0.105106466}},"KneeRight":{"JointType":17,"Orientation":{"X":0.542817,"Y":-0.2760897,"Z":0.6829669,"W":-0.403336436}},"AnkleRight":{"JointType":18,"Orientation":{"X":0.7097488,"Y":-0.154791877,"Z":0.609968066,"W":-0.3165991}},"FootRight":{"JointType":19,"Orientation":{"X":0.0,"Y":0.0,"Z":0.0,"W":0.0}},"SpineShoulder":{"JointType":20,"Orientation":{"X":-0.0259389449,"Y":0.9344146,"Z":-0.0472211652,"W":0.352088869}},"HandTipLeft":{"JointType":21,"Orientation":{"X":0.0,"Y":0.0,"Z":0.0,"W":0.0}},"ThumbLeft":{"JointType":22,"Orientation":{"X":0.0,"Y":0.0,"Z":0.0,"W":0.0}},"HandTipRight":{"JointType":23,"Orientation":{"X":0.0,"Y":0.0,"Z":0.0,"W":0.0}},"ThumbRight":{"JointType":24,"Orientation":{"X":0.0,"Y":0.0,"Z":0.0,"W":0.0}}},"Joints":{"SpineBase":{"JointType":0,"Position":{"X":-0.02053417,"Y":0.100622065,"Z":1.87090755},"TrackingState":2},"SpineMid":{"JointType":1,"Position":{"X":-0.0264948681,"Y":0.452126235,"Z":1.84493268},"TrackingState":2},"Neck":{"JointType":2,"Position":{"X":-0.0314659327,"Y":0.7846192,"Z":1.80614138},"TrackingState":2},"Head":{"JointType":3,"Position":{"X":-0.0012602018,"Y":0.9268866,"Z":1.79581606},"TrackingState":2},"ShoulderLeft":{"JointType":4,"Position":{"X":-0.144134939,"Y":0.619414568,"Z":1.69178855},"TrackingState":2},"ElbowLeft":{"JointType":5,"Position":{"X":-0.06302545,"Y":0.523524,"Z":1.47327924},"TrackingState":2},"WristLeft":{"JointType":6,"Position":{"X":0.125856847,"Y":0.4792084,"Z":1.32515013},"TrackingState":2},"HandLeft":{"JointType":7,"Position":{"X":0.219872415,"Y":0.4544419,"Z":1.27240956},"TrackingState":2},"ShoulderRight":{"JointType":8,"Position":{"X":0.106571943,"Y":0.6037159,"Z":1.93721128},"TrackingState":1},"ElbowRight":{"JointType":9,"Position":{"X":0.1444736,"Y":0.5532124,"Z":2.22938156},"TrackingState":2},"WristRight":{"JointType":10,"Position":{"X":0.1963053,"Y":0.442135036,"Z":2.463304},"TrackingState":2},"HandRight":{"JointType":11,"Position":{"X":0.21539557,"Y":0.418848068,"Z":2.50113368},"TrackingState":2},"HipLeft":{"JointType":12,"Position":{"X":-0.0843736,"Y":0.09670763,"Z":1.81641579},"TrackingState":2},"KneeLeft":{"JointType":13,"Position":{"X":-0.0717033744,"Y":-0.227669731,"Z":1.86923456},"TrackingState":2},"AnkleLeft":{"JointType":14,"Position":{"X":-0.0576017834,"Y":-0.6304719,"Z":2.00157261},"TrackingState":2},"FootLeft":{"JointType":15,"Position":{"X":-0.0433043242,"Y":-0.7085176,"Z":1.9292413},"TrackingState":2},"HipRight":{"JointType":16,"Position":{"X":0.0453116558,"Y":0.09933345,"Z":1.84491444},"TrackingState":2},"KneeRight":{"JointType":17,"Position":{"X":0.137091622,"Y":-0.09145754,"Z":1.54714084},"TrackingState":2},"AnkleRight":{"JointType":18,"Position":{"X":0.199182838,"Y":-0.371740967,"Z":1.309131},"TrackingState":2},"FootRight":{"JointType":19,"Position":{"X":0.195658311,"Y":-0.3836335,"Z":1.19189024},"TrackingState":2},"SpineShoulder":{"JointType":20,"Position":{"X":-0.0303518418,"Y":0.7040142,"Z":1.81794643},"TrackingState":2},"HandTipLeft":{"JointType":21,"Position":{"X":0.28661716,"Y":0.426370144,"Z":1.26096773},"TrackingState":2},"ThumbLeft":{"JointType":22,"Position":{"X":0.238033623,"Y":0.471969724,"Z":1.25535715},"TrackingState":2},"HandTipRight":{"JointType":23,"Position":{"X":0.2385955,"Y":0.368697673,"Z":2.56474},"TrackingState":2},"ThumbRight":{"JointType":24,"Position":{"X":0.196638644,"Y":0.4178348,"Z":2.523},"TrackingState":2}},"LeanTrackingState":2,"TrackingId":72057594037929101},{"Lean":{"X":0.0,"Y":0.0},"Activities":{"EyeLeftClosed":0,"EyeRightClosed":0,"MouthOpen":0,"MouthMoved":0,"LookingAway":0},"Appearance":{"WearingGlasses":0},"ClippedEdges":0,"Engaged":0,"Expressions":{"Neutral":0,"Happy":0},"HandLeftConfidence":1,"HandLeftState":1,"HandRightConfidence":1,"HandRightState":1,"IsRestricted":false,"IsTracked":false,"JointOrientations":{"SpineBase":{"JointType":0,"Orientation":{"X":0.0,"Y":0.0,"Z":0.0,"W":0.0}},"SpineMid":{"JointType":1,"Orientation":{"X":0.0,"Y":0.0,"Z":0.0,"W":0.0}},"Neck":{"JointType":2,"Orientation":{"X":0.0,"Y":0.0,"Z":0.0,"W":0.0}},"Head":{"JointType":3,"Orientation":{"X":0.0,"Y":0.0,"Z":0.0,"W":0.0}},"ShoulderLeft":{"JointType":4,"Orientation":{"X":0.0,"Y":0.0,"Z":0.0,"W":0.0}},"ElbowLeft":{"JointType":5,"Orientation":{"X":0.0,"Y":0.0,"Z":0.0,"W":0.0}},"WristLeft":{"JointType":6,"Orientation":{"X":0.0,"Y":0.0,"Z":0.0,"W":0.0}},"HandLeft":{"JointType":7,"Orientation":{"X":0.0,"Y":0.0,"Z":0.0,"W":0.0}},"ShoulderRight":{"JointType":8,"Orientation":{"X":0.0,"Y":0.0,"Z":0.0,"W":0.0}},"ElbowRight":{"JointType":9,"Orientation":{"X":0.0,"Y":0.0,"Z":0.0,"W":0.0}},"WristRight":{"JointType":10,"Orientation":{"X":0.0,"Y":0.0,"Z":0.0,"W":0.0}},"HandRight":{"JointType":11,"Orientation":{"X":0.0,"Y":0.0,"Z":0.0,"W":0.0}},"HipLeft":{"JointType":12,"Orientation":{"X":0.0,"Y":0.0,"Z":0.0,"W":0.0}},"KneeLeft":{"JointType":13,"Orientation":{"X":0.0,"Y":0.0,"Z":0.0,"W":0.0}},"AnkleLeft":{"JointType":14,"Orientation":{"X":0.0,"Y":0.0,"Z":0.0,"W":0.0}},"FootLeft":{"JointType":15,"Orientation":{"X":0.0,"Y":0.0,"Z":0.0,"W":0.0}},"HipRight":{"JointType":16,"Orientation":{"X":0.0,"Y":0.0,"Z":0.0,"W":0.0}},"KneeRight":{"JointType":17,"Orientation":{"X":0.0,"Y":0.0,"Z":0.0,"W":0.0}},"AnkleRight":{"JointType":18,"Orientation":{"X":0.0,"Y":0.0,"Z":0.0,"W":0.0}},"FootRight":{"JointType":19,"Orientation":{"X":0.0,"Y":0.0,"Z":0.0,"W":0.0}},"SpineShoulder":{"JointType":20,"Orientation":{"X":0.0,"Y":0.0,"Z":0.0,"W":0.0}},"HandTipLeft":{"JointType":21,"Orientation":{"X":0.0,"Y":0.0,"Z":0.0,"W":0.0}},"ThumbLeft":{"JointType":22,"Orientation":{"X":0.0,"Y":0.0,"Z":0.0,"W":0.0}},"HandTipRight":{"JointType":23,"Orientation":{"X":0.0,"Y":0.0,"Z":0.0,"W":0.0}},"ThumbRight":{"JointType":24,"Orientation":{"X":0.0,"Y":0.0,"Z":0.0,"W":0.0}}},"Joints":{"SpineBase":{"JointType":0,"Position":{"X":0.0,"Y":0.0,"Z":0.0},"TrackingState":0},"SpineMid":{"JointType":1,"Position":{"X":0.0,"Y":0.0,"Z":0.0},"TrackingState":0},"Neck":{"JointType":2,"Position":{"X":0.0,"Y":0.0,"Z":0.0},"TrackingState":0},"Head":{"JointType":3,"Position":{"X":0.0,"Y":0.0,"Z":0.0},"TrackingState":0},"ShoulderLeft":{"JointType":4,"Position":{"X":0.0,"Y":0.0,"Z":0.0},"TrackingState":0},"ElbowLeft":{"JointType":5,"Position":{"X":0.0,"Y":0.0,"Z":0.0},"TrackingState":0},"WristLeft":{"JointType":6,"Position":{"X":0.0,"Y":0.0,"Z":0.0},"TrackingState":0},"HandLeft":{"JointType":7,"Position":{"X":0.0,"Y":0.0,"Z":0.0},"TrackingState":0},"ShoulderRight":{"JointType":8,"Position":{"X":0.0,"Y":0.0,"Z":0.0},"TrackingState":0},"ElbowRight":{"JointType":9,"Position":{"X":0.0,"Y":0.0,"Z":0.0},"TrackingState":0},"WristRight":{"JointType":10,"Position":{"X":0.0,"Y":0.0,"Z":0.0},"TrackingState":0},"HandRight":{"JointType":11,"Position":{"X":0.0,"Y":0.0,"Z":0.0},"TrackingState":0},"HipLeft":{"JointType":12,"Position":{"X":0.0,"Y":0.0,"Z":0.0},"TrackingState":0},"KneeLeft":{"JointType":13,"Position":{"X":0.0,"Y":0.0,"Z":0.0},"TrackingState":0},"AnkleLeft":{"JointType":14,"Position":{"X":0.0,"Y":0.0,"Z":0.0},"TrackingState":0},"FootLeft":{"JointType":15,"Position":{"X":0.0,"Y":0.0,"Z":0.0},"TrackingState":0},"HipRight":{"JointType":16,"Position":{"X":0.0,"Y":0.0,"Z":0.0},"TrackingState":0},"KneeRight":{"JointType":17,"Position":{"X":0.0,"Y":0.0,"Z":0.0},"TrackingState":0},"AnkleRight":{"JointType":18,"Position":{"X":0.0,"Y":0.0,"Z":0.0},"TrackingState":0},"FootRight":{"JointType":19,"Position":{"X":0.0,"Y":0.0,"Z":0.0},"TrackingState":0},"SpineShoulder":{"JointType":20,"Position":{"X":0.0,"Y":0.0,"Z":0.0},"TrackingState":0},"HandTipLeft":{"JointType":21,"Position":{"X":0.0,"Y":0.0,"Z":0.0},"TrackingState":0},"ThumbLeft":{"JointType":22,"Position":{"X":0.0,"Y":0.0,"Z":0.0},"TrackingState":0},"HandTipRight":{"JointType":23,"Position":{"X":0.0,"Y":0.0,"Z":0.0},"TrackingState":0},"ThumbRight":{"JointType":24,"Position":{"X":0.0,"Y":0.0,"Z":0.0},"TrackingState":0}},"LeanTrackingState":0,"TrackingId":0},{"Lean":{"X":0.0,"Y":0.0},"Activities":{"EyeLeftClosed":0,"EyeRightClosed":0,"MouthOpen":0,"MouthMoved":0,"LookingAway":0},"Appearance":{"WearingGlasses":0},"ClippedEdges":0,"Engaged":0,"Expressions":{"Neutral":0,"Happy":0},"HandLeftConfidence":1,"HandLeftState":1,"HandRightConfidence":1,"HandRightState":1,"IsRestricted":false,"IsTracked":false,"JointOrientations":{"SpineBase":{"JointType":0,"Orientation":{"X":0.0,"Y":0.0,"Z":0.0,"W":0.0}},"SpineMid":{"JointType":1,"Orientation":{"X":0.0,"Y":0.0,"Z":0.0,"W":0.0}},"Neck":{"JointType":2,"Orientation":{"X":0.0,"Y":0.0,"Z":0.0,"W":0.0}},"Head":{"JointType":3,"Orientation":{"X":0.0,"Y":0.0,"Z":0.0,"W":0.0}},"ShoulderLeft":{"JointType":4,"Orientation":{"X":0.0,"Y":0.0,"Z":0.0,"W":0.0}},"ElbowLeft":{"JointType":5,"Orientation":{"X":0.0,"Y":0.0,"Z":0.0,"W":0.0}},"WristLeft":{"JointType":6,"Orientation":{"X":0.0,"Y":0.0,"Z":0.0,"W":0.0}},"HandLeft":{"JointType":7,"Orientation":{"X":0.0,"Y":0.0,"Z":0.0,"W":0.0}},"ShoulderRight":{"JointType":8,"Orientation":{"X":0.0,"Y":0.0,"Z":0.0,"W":0.0}},"ElbowRight":{"JointType":9,"Orientation":{"X":0.0,"Y":0.0,"Z":0.0,"W":0.0}},"WristRight":{"JointType":10,"Orientation":{"X":0.0,"Y":0.0,"Z":0.0,"W":0.0}},"HandRight":{"JointType":11,"Orientation":{"X":0.0,"Y":0.0,"Z":0.0,"W":0.0}},"HipLeft":{"JointType":12,"Orientation":{"X":0.0,"Y":0.0,"Z":0.0,"W":0.0}},"KneeLeft":{"JointType":13,"Orientation":{"X":0.0,"Y":0.0,"Z":0.0,"W":0.0}},"AnkleLeft":{"JointType":14,"Orientation":{"X":0.0,"Y":0.0,"Z":0.0,"W":0.0}},"FootLeft":{"JointType":15,"Orientation":{"X":0.0,"Y":0.0,"Z":0.0,"W":0.0}},"HipRight":{"JointType":16,"Orientation":{"X":0.0,"Y":0.0,"Z":0.0,"W":0.0}},"KneeRight":{"JointType":17,"Orientation":{"X":0.0,"Y":0.0,"Z":0.0,"W":0.0}},"AnkleRight":{"JointType":18,"Orientation":{"X":0.0,"Y":0.0,"Z":0.0,"W":0.0}},"FootRight":{"JointType":19,"Orientation":{"X":0.0,"Y":0.0,"Z":0.0,"W":0.0}},"SpineShoulder":{"JointType":20,"Orientation":{"X":0.0,"Y":0.0,"Z":0.0,"W":0.0}},"HandTipLeft":{"JointType":21,"Orientation":{"X":0.0,"Y":0.0,"Z":0.0,"W":0.0}},"ThumbLeft":{"JointType":22,"Orientation":{"X":0.0,"Y":0.0,"Z":0.0,"W":0.0}},"HandTipRight":{"JointType":23,"Orientation":{"X":0.0,"Y":0.0,"Z":0.0,"W":0.0}},"ThumbRight":{"JointType":24,"Orientation":{"X":0.0,"Y":0.0,"Z":0.0,"W":0.0}}},"Joints":{"SpineBase":{"JointType":0,"Position":{"X":0.0,"Y":0.0,"Z":0.0},"TrackingState":0},"SpineMid":{"JointType":1,"Position":{"X":0.0,"Y":0.0,"Z":0.0},"TrackingState":0},"Neck":{"JointType":2,"Position":{"X":0.0,"Y":0.0,"Z":0.0},"TrackingState":0},"Head":{"JointType":3,"Position":{"X":0.0,"Y":0.0,"Z":0.0},"TrackingState":0},"ShoulderLeft":{"JointType":4,"Position":{"X":0.0,"Y":0.0,"Z":0.0},"TrackingState":0},"ElbowLeft":{"JointType":5,"Position":{"X":0.0,"Y":0.0,"Z":0.0},"TrackingState":0},"WristLeft":{"JointType":6,"Position":{"X":0.0,"Y":0.0,"Z":0.0},"TrackingState":0},"HandLeft":{"JointType":7,"Position":{"X":0.0,"Y":0.0,"Z":0.0},"TrackingState":0},"ShoulderRight":{"JointType":8,"Position":{"X":0.0,"Y":0.0,"Z":0.0},"TrackingState":0},"ElbowRight":{"JointType":9,"Position":{"X":0.0,"Y":0.0,"Z":0.0},"TrackingState":0},"WristRight":{"JointType":10,"Position":{"X":0.0,"Y":0.0,"Z":0.0},"TrackingState":0},"HandRight":{"JointType":11,"Position":{"X":0.0,"Y":0.0,"Z":0.0},"TrackingState":0},"HipLeft":{"JointType":12,"Position":{"X":0.0,"Y":0.0,"Z":0.0},"TrackingState":0},"KneeLeft":{"JointType":13,"Position":{"X":0.0,"Y":0.0,"Z":0.0},"TrackingState":0},"AnkleLeft":{"JointType":14,"Position":{"X":0.0,"Y":0.0,"Z":0.0},"TrackingState":0},"FootLeft":{"JointType":15,"Position":{"X":0.0,"Y":0.0,"Z":0.0},"TrackingState":0},"HipRight":{"JointType":16,"Position":{"X":0.0,"Y":0.0,"Z":0.0},"TrackingState":0},"KneeRight":{"JointType":17,"Position":{"X":0.0,"Y":0.0,"Z":0.0},"TrackingState":0},"AnkleRight":{"JointType":18,"Position":{"X":0.0,"Y":0.0,"Z":0.0},"TrackingState":0},"FootRight":{"JointType":19,"Position":{"X":0.0,"Y":0.0,"Z":0.0},"TrackingState":0},"SpineShoulder":{"JointType":20,"Position":{"X":0.0,"Y":0.0,"Z":0.0},"TrackingState":0},"HandTipLeft":{"JointType":21,"Position":{"X":0.0,"Y":0.0,"Z":0.0},"TrackingState":0},"ThumbLeft":{"JointType":22,"Position":{"X":0.0,"Y":0.0,"Z":0.0},"TrackingState":0},"HandTipRight":{"JointType":23,"Position":{"X":0.0,"Y":0.0,"Z":0.0},"TrackingState":0},"ThumbRight":{"JointType":24,"Position":{"X":0.0,"Y":0.0,"Z":0.0},"TrackingState":0}},"LeanTrackingState":0,"TrackingId":0},{"Lean":{"X":0.0,"Y":0.0},"Activities":{"EyeLeftClosed":0,"EyeRightClosed":0,"MouthOpen":0,"MouthMoved":0,"LookingAway":0},"Appearance":{"WearingGlasses":0},"ClippedEdges":0,"Engaged":0,"Expressions":{"Neutral":0,"Happy":0},"HandLeftConfidence":1,"HandLeftState":1,"HandRightConfidence":1,"HandRightState":1,"IsRestricted":false,"IsTracked":false,"JointOrientations":{"SpineBase":{"JointType":0,"Orientation":{"X":0.0,"Y":0.0,"Z":0.0,"W":0.0}},"SpineMid":{"JointType":1,"Orientation":{"X":0.0,"Y":0.0,"Z":0.0,"W":0.0}},"Neck":{"JointType":2,"Orientation":{"X":0.0,"Y":0.0,"Z":0.0,"W":0.0}},"Head":{"JointType":3,"Orientation":{"X":0.0,"Y":0.0,"Z":0.0,"W":0.0}},"ShoulderLeft":{"JointType":4,"Orientation":{"X":0.0,"Y":0.0,"Z":0.0,"W":0.0}},"ElbowLeft":{"JointType":5,"Orientation":{"X":0.0,"Y":0.0,"Z":0.0,"W":0.0}},"WristLeft":{"JointType":6,"Orientation":{"X":0.0,"Y":0.0,"Z":0.0,"W":0.0}},"HandLeft":{"JointType":7,"Orientation":{"X":0.0,"Y":0.0,"Z":0.0,"W":0.0}},"ShoulderRight":{"JointType":8,"Orientation":{"X":0.0,"Y":0.0,"Z":0.0,"W":0.0}},"ElbowRight":{"JointType":9,"Orientation":{"X":0.0,"Y":0.0,"Z":0.0,"W":0.0}},"WristRight":{"JointType":10,"Orientation":{"X":0.0,"Y":0.0,"Z":0.0,"W":0.0}},"HandRight":{"JointType":11,"Orientation":{"X":0.0,"Y":0.0,"Z":0.0,"W":0.0}},"HipLeft":{"JointType":12,"Orientation":{"X":0.0,"Y":0.0,"Z":0.0,"W":0.0}},"KneeLeft":{"JointType":13,"Orientation":{"X":0.0,"Y":0.0,"Z":0.0,"W":0.0}},"AnkleLeft":{"JointType":14,"Orientation":{"X":0.0,"Y":0.0,"Z":0.0,"W":0.0}},"FootLeft":{"JointType":15,"Orientation":{"X":0.0,"Y":0.0,"Z":0.0,"W":0.0}},"HipRight":{"JointType":16,"Orientation":{"X":0.0,"Y":0.0,"Z":0.0,"W":0.0}},"KneeRight":{"JointType":17,"Orientation":{"X":0.0,"Y":0.0,"Z":0.0,"W":0.0}},"AnkleRight":{"JointType":18,"Orientation":{"X":0.0,"Y":0.0,"Z":0.0,"W":0.0}},"FootRight":{"JointType":19,"Orientation":{"X":0.0,"Y":0.0,"Z":0.0,"W":0.0}},"SpineShoulder":{"JointType":20,"Orientation":{"X":0.0,"Y":0.0,"Z":0.0,"W":0.0}},"HandTipLeft":{"JointType":21,"Orientation":{"X":0.0,"Y":0.0,"Z":0.0,"W":0.0}},"ThumbLeft":{"JointType":22,"Orientation":{"X":0.0,"Y":0.0,"Z":0.0,"W":0.0}},"HandTipRight":{"JointType":23,"Orientation":{"X":0.0,"Y":0.0,"Z":0.0,"W":0.0}},"ThumbRight":{"JointType":24,"Orientation":{"X":0.0,"Y":0.0,"Z":0.0,"W":0.0}}},"Joints":{"SpineBase":{"JointType":0,"Position":{"X":0.0,"Y":0.0,"Z":0.0},"TrackingState":0},"SpineMid":{"JointType":1,"Position":{"X":0.0,"Y":0.0,"Z":0.0},"TrackingState":0},"Neck":{"JointType":2,"Position":{"X":0.0,"Y":0.0,"Z":0.0},"TrackingState":0},"Head":{"JointType":3,"Position":{"X":0.0,"Y":0.0,"Z":0.0},"TrackingState":0},"ShoulderLeft":{"JointType":4,"Position":{"X":0.0,"Y":0.0,"Z":0.0},"TrackingState":0},"ElbowLeft":{"JointType":5,"Position":{"X":0.0,"Y":0.0,"Z":0.0},"TrackingState":0},"WristLeft":{"JointType":6,"Position":{"X":0.0,"Y":0.0,"Z":0.0},"TrackingState":0},"HandLeft":{"JointType":7,"Position":{"X":0.0,"Y":0.0,"Z":0.0},"TrackingState":0},"ShoulderRight":{"JointType":8,"Position":{"X":0.0,"Y":0.0,"Z":0.0},"TrackingState":0},"ElbowRight":{"JointType":9,"Position":{"X":0.0,"Y":0.0,"Z":0.0},"TrackingState":0},"WristRight":{"JointType":10,"Position":{"X":0.0,"Y":0.0,"Z":0.0},"TrackingState":0},"HandRight":{"JointType":11,"Position":{"X":0.0,"Y":0.0,"Z":0.0},"TrackingState":0},"HipLeft":{"JointType":12,"Position":{"X":0.0,"Y":0.0,"Z":0.0},"TrackingState":0},"KneeLeft":{"JointType":13,"Position":{"X":0.0,"Y":0.0,"Z":0.0},"TrackingState":0},"AnkleLeft":{"JointType":14,"Position":{"X":0.0,"Y":0.0,"Z":0.0},"TrackingState":0},"FootLeft":{"JointType":15,"Position":{"X":0.0,"Y":0.0,"Z":0.0},"TrackingState":0},"HipRight":{"JointType":16,"Position":{"X":0.0,"Y":0.0,"Z":0.0},"TrackingState":0},"KneeRight":{"JointType":17,"Position":{"X":0.0,"Y":0.0,"Z":0.0},"TrackingState":0},"AnkleRight":{"JointType":18,"Position":{"X":0.0,"Y":0.0,"Z":0.0},"TrackingState":0},"FootRight":{"JointType":19,"Position":{"X":0.0,"Y":0.0,"Z":0.0},"TrackingState":0},"SpineShoulder":{"JointType":20,"Position":{"X":0.0,"Y":0.0,"Z":0.0},"TrackingState":0},"HandTipLeft":{"JointType":21,"Position":{"X":0.0,"Y":0.0,"Z":0.0},"TrackingState":0},"ThumbLeft":{"JointType":22,"Position":{"X":0.0,"Y":0.0,"Z":0.0},"TrackingState":0},"HandTipRight":{"JointType":23,"Position":{"X":0.0,"Y":0.0,"Z":0.0},"TrackingState":0},"ThumbRight":{"JointType":24,"Position":{"X":0.0,"Y":0.0,"Z":0.0},"TrackingState":0}},"LeanTrackingState":0,"TrackingId":0},{"Lean":{"X":0.0,"Y":0.0},"Activities":{"EyeLeftClosed":0,"EyeRightClosed":0,"MouthOpen":0,"MouthMoved":0,"LookingAway":0},"Appearance":{"WearingGlasses":0},"ClippedEdges":0,"Engaged":0,"Expressions":{"Neutral":0,"Happy":0},"HandLeftConfidence":1,"HandLeftState":1,"HandRightConfidence":1,"HandRightState":1,"IsRestricted":false,"IsTracked":false,"JointOrientations":{"SpineBase":{"JointType":0,"Orientation":{"X":0.0,"Y":0.0,"Z":0.0,"W":0.0}},"SpineMid":{"JointType":1,"Orientation":{"X":0.0,"Y":0.0,"Z":0.0,"W":0.0}},"Neck":{"JointType":2,"Orientation":{"X":0.0,"Y":0.0,"Z":0.0,"W":0.0}},"Head":{"JointType":3,"Orientation":{"X":0.0,"Y":0.0,"Z":0.0,"W":0.0}},"ShoulderLeft":{"JointType":4,"Orientation":{"X":0.0,"Y":0.0,"Z":0.0,"W":0.0}},"ElbowLeft":{"JointType":5,"Orientation":{"X":0.0,"Y":0.0,"Z":0.0,"W":0.0}},"WristLeft":{"JointType":6,"Orientation":{"X":0.0,"Y":0.0,"Z":0.0,"W":0.0}},"HandLeft":{"JointType":7,"Orientation":{"X":0.0,"Y":0.0,"Z":0.0,"W":0.0}},"ShoulderRight":{"JointType":8,"Orientation":{"X":0.0,"Y":0.0,"Z":0.0,"W":0.0}},"ElbowRight":{"JointType":9,"Orientation":{"X":0.0,"Y":0.0,"Z":0.0,"W":0.0}},"WristRight":{"JointType":10,"Orientation":{"X":0.0,"Y":0.0,"Z":0.0,"W":0.0}},"HandRight":{"JointType":11,"Orientation":{"X":0.0,"Y":0.0,"Z":0.0,"W":0.0}},"HipLeft":{"JointType":12,"Orientation":{"X":0.0,"Y":0.0,"Z":0.0,"W":0.0}},"KneeLeft":{"JointType":13,"Orientation":{"X":0.0,"Y":0.0,"Z":0.0,"W":0.0}},"AnkleLeft":{"JointType":14,"Orientation":{"X":0.0,"Y":0.0,"Z":0.0,"W":0.0}},"FootLeft":{"JointType":15,"Orientation":{"X":0.0,"Y":0.0,"Z":0.0,"W":0.0}},"HipRight":{"JointType":16,"Orientation":{"X":0.0,"Y":0.0,"Z":0.0,"W":0.0}},"KneeRight":{"JointType":17,"Orientation":{"X":0.0,"Y":0.0,"Z":0.0,"W":0.0}},"AnkleRight":{"JointType":18,"Orientation":{"X":0.0,"Y":0.0,"Z":0.0,"W":0.0}},"FootRight":{"JointType":19,"Orientation":{"X":0.0,"Y":0.0,"Z":0.0,"W":0.0}},"SpineShoulder":{"JointType":20,"Orientation":{"X":0.0,"Y":0.0,"Z":0.0,"W":0.0}},"HandTipLeft":{"JointType":21,"Orientation":{"X":0.0,"Y":0.0,"Z":0.0,"W":0.0}},"ThumbLeft":{"JointType":22,"Orientation":{"X":0.0,"Y":0.0,"Z":0.0,"W":0.0}},"HandTipRight":{"JointType":23,"Orientation":{"X":0.0,"Y":0.0,"Z":0.0,"W":0.0}},"ThumbRight":{"JointType":24,"Orientation":{"X":0.0,"Y":0.0,"Z":0.0,"W":0.0}}},"Joints":{"SpineBase":{"JointType":0,"Position":{"X":0.0,"Y":0.0,"Z":0.0},"TrackingState":0},"SpineMid":{"JointType":1,"Position":{"X":0.0,"Y":0.0,"Z":0.0},"TrackingState":0},"Neck":{"JointType":2,"Position":{"X":0.0,"Y":0.0,"Z":0.0},"TrackingState":0},"Head":{"JointType":3,"Position":{"X":0.0,"Y":0.0,"Z":0.0},"TrackingState":0},"ShoulderLeft":{"JointType":4,"Position":{"X":0.0,"Y":0.0,"Z":0.0},"TrackingState":0},"ElbowLeft":{"JointType":5,"Position":{"X":0.0,"Y":0.0,"Z":0.0},"TrackingState":0},"WristLeft":{"JointType":6,"Position":{"X":0.0,"Y":0.0,"Z":0.0},"TrackingState":0},"HandLeft":{"JointType":7,"Position":{"X":0.0,"Y":0.0,"Z":0.0},"TrackingState":0},"ShoulderRight":{"JointType":8,"Position":{"X":0.0,"Y":0.0,"Z":0.0},"TrackingState":0},"ElbowRight":{"JointType":9,"Position":{"X":0.0,"Y":0.0,"Z":0.0},"TrackingState":0},"WristRight":{"JointType":10,"Position":{"X":0.0,"Y":0.0,"Z":0.0},"TrackingState":0},"HandRight":{"JointType":11,"Position":{"X":0.0,"Y":0.0,"Z":0.0},"TrackingState":0},"HipLeft":{"JointType":12,"Position":{"X":0.0,"Y":0.0,"Z":0.0},"TrackingState":0},"KneeLeft":{"JointType":13,"Position":{"X":0.0,"Y":0.0,"Z":0.0},"TrackingState":0},"AnkleLeft":{"JointType":14,"Position":{"X":0.0,"Y":0.0,"Z":0.0},"TrackingState":0},"FootLeft":{"JointType":15,"Position":{"X":0.0,"Y":0.0,"Z":0.0},"TrackingState":0},"HipRight":{"JointType":16,"Position":{"X":0.0,"Y":0.0,"Z":0.0},"TrackingState":0},"KneeRight":{"JointType":17,"Position":{"X":0.0,"Y":0.0,"Z":0.0},"TrackingState":0},"AnkleRight":{"JointType":18,"Position":{"X":0.0,"Y":0.0,"Z":0.0},"TrackingState":0},"FootRight":{"JointType":19,"Position":{"X":0.0,"Y":0.0,"Z":0.0},"TrackingState":0},"SpineShoulder":{"JointType":20,"Position":{"X":0.0,"Y":0.0,"Z":0.0},"TrackingState":0},"HandTipLeft":{"JointType":21,"Position":{"X":0.0,"Y":0.0,"Z":0.0},"TrackingState":0},"ThumbLeft":{"JointType":22,"Position":{"X":0.0,"Y":0.0,"Z":0.0},"TrackingState":0},"HandTipRight":{"JointType":23,"Position":{"X":0.0,"Y":0.0,"Z":0.0},"TrackingState":0},"ThumbRight":{"JointType":24,"Position":{"X":0.0,"Y":0.0,"Z":0.0},"TrackingState":0}},"LeanTrackingState":0,"TrackingId":0},{"Lean":{"X":0.0,"Y":0.0},"Activities":{"EyeLeftClosed":0,"EyeRightClosed":0,"MouthOpen":0,"MouthMoved":0,"LookingAway":0},"Appearance":{"WearingGlasses":0},"ClippedEdges":0,"Engaged":0,"Expressions":{"Neutral":0,"Happy":0},"HandLeftConfidence":1,"HandLeftState":1,"HandRightConfidence":1,"HandRightState":1,"IsRestricted":false,"IsTracked":false,"JointOrientations":{"SpineBase":{"JointType":0,"Orientation":{"X":0.0,"Y":0.0,"Z":0.0,"W":0.0}},"SpineMid":{"JointType":1,"Orientation":{"X":0.0,"Y":0.0,"Z":0.0,"W":0.0}},"Neck":{"JointType":2,"Orientation":{"X":0.0,"Y":0.0,"Z":0.0,"W":0.0}},"Head":{"JointType":3,"Orientation":{"X":0.0,"Y":0.0,"Z":0.0,"W":0.0}},"ShoulderLeft":{"JointType":4,"Orientation":{"X":0.0,"Y":0.0,"Z":0.0,"W":0.0}},"ElbowLeft":{"JointType":5,"Orientation":{"X":0.0,"Y":0.0,"Z":0.0,"W":0.0}},"WristLeft":{"JointType":6,"Orientation":{"X":0.0,"Y":0.0,"Z":0.0,"W":0.0}},"HandLeft":{"JointType":7,"Orientation":{"X":0.0,"Y":0.0,"Z":0.0,"W":0.0}},"ShoulderRight":{"JointType":8,"Orientation":{"X":0.0,"Y":0.0,"Z":0.0,"W":0.0}},"ElbowRight":{"JointType":9,"Orientation":{"X":0.0,"Y":0.0,"Z":0.0,"W":0.0}},"WristRight":{"JointType":10,"Orientation":{"X":0.0,"Y":0.0,"Z":0.0,"W":0.0}},"HandRight":{"JointType":11,"Orientation":{"X":0.0,"Y":0.0,"Z":0.0,"W":0.0}},"HipLeft":{"JointType":12,"Orientation":{"X":0.0,"Y":0.0,"Z":0.0,"W":0.0}},"KneeLeft":{"JointType":13,"Orientation":{"X":0.0,"Y":0.0,"Z":0.0,"W":0.0}},"AnkleLeft":{"JointType":14,"Orientation":{"X":0.0,"Y":0.0,"Z":0.0,"W":0.0}},"FootLeft":{"JointType":15,"Orientation":{"X":0.0,"Y":0.0,"Z":0.0,"W":0.0}},"HipRight":{"JointType":16,"Orientation":{"X":0.0,"Y":0.0,"Z":0.0,"W":0.0}},"KneeRight":{"JointType":17,"Orientation":{"X":0.0,"Y":0.0,"Z":0.0,"W":0.0}},"AnkleRight":{"JointType":18,"Orientation":{"X":0.0,"Y":0.0,"Z":0.0,"W":0.0}},"FootRight":{"JointType":19,"Orientation":{"X":0.0,"Y":0.0,"Z":0.0,"W":0.0}},"SpineShoulder":{"JointType":20,"Orientation":{"X":0.0,"Y":0.0,"Z":0.0,"W":0.0}},"HandTipLeft":{"JointType":21,"Orientation":{"X":0.0,"Y":0.0,"Z":0.0,"W":0.0}},"ThumbLeft":{"JointType":22,"Orientation":{"X":0.0,"Y":0.0,"Z":0.0,"W":0.0}},"HandTipRight":{"JointType":23,"Orientation":{"X":0.0,"Y":0.0,"Z":0.0,"W":0.0}},"ThumbRight":{"JointType":24,"Orientation":{"X":0.0,"Y":0.0,"Z":0.0,"W":0.0}}},"Joints":{"SpineBase":{"JointType":0,"Position":{"X":0.0,"Y":0.0,"Z":0.0},"TrackingState":0},"SpineMid":{"JointType":1,"Position":{"X":0.0,"Y":0.0,"Z":0.0},"TrackingState":0},"Neck":{"JointType":2,"Position":{"X":0.0,"Y":0.0,"Z":0.0},"TrackingState":0},"Head":{"JointType":3,"Position":{"X":0.0,"Y":0.0,"Z":0.0},"TrackingState":0},"ShoulderLeft":{"JointType":4,"Position":{"X":0.0,"Y":0.0,"Z":0.0},"TrackingState":0},"ElbowLeft":{"JointType":5,"Position":{"X":0.0,"Y":0.0,"Z":0.0},"TrackingState":0},"WristLeft":{"JointType":6,"Position":{"X":0.0,"Y":0.0,"Z":0.0},"TrackingState":0},"HandLeft":{"JointType":7,"Position":{"X":0.0,"Y":0.0,"Z":0.0},"TrackingState":0},"ShoulderRight":{"JointType":8,"Position":{"X":0.0,"Y":0.0,"Z":0.0},"TrackingState":0},"ElbowRight":{"JointType":9,"Position":{"X":0.0,"Y":0.0,"Z":0.0},"TrackingState":0},"WristRight":{"JointType":10,"Position":{"X":0.0,"Y":0.0,"Z":0.0},"TrackingState":0},"HandRight":{"JointType":11,"Position":{"X":0.0,"Y":0.0,"Z":0.0},"TrackingState":0},"HipLeft":{"JointType":12,"Position":{"X":0.0,"Y":0.0,"Z":0.0},"TrackingState":0},"KneeLeft":{"JointType":13,"Position":{"X":0.0,"Y":0.0,"Z":0.0},"TrackingState":0},"AnkleLeft":{"JointType":14,"Position":{"X":0.0,"Y":0.0,"Z":0.0},"TrackingState":0},"FootLeft":{"JointType":15,"Position":{"X":0.0,"Y":0.0,"Z":0.0},"TrackingState":0},"HipRight":{"JointType":16,"Position":{"X":0.0,"Y":0.0,"Z":0.0},"TrackingState":0},"KneeRight":{"JointType":17,"Position":{"X":0.0,"Y":0.0,"Z":0.0},"TrackingState":0},"AnkleRight":{"JointType":18,"Position":{"X":0.0,"Y":0.0,"Z":0.0},"TrackingState":0},"FootRight":{"JointType":19,"Position":{"X":0.0,"Y":0.0,"Z":0.0},"TrackingState":0},"SpineShoulder":{"JointType":20,"Position":{"X":0.0,"Y":0.0,"Z":0.0},"TrackingState":0},"HandTipLeft":{"JointType":21,"Position":{"X":0.0,"Y":0.0,"Z":0.0},"TrackingState":0},"ThumbLeft":{"JointType":22,"Position":{"X":0.0,"Y":0.0,"Z":0.0},"TrackingState":0},"HandTipRight":{"JointType":23,"Position":{"X":0.0,"Y":0.0,"Z":0.0},"TrackingState":0},"ThumbRight":{"JointType":24,"Position":{"X":0.0,"Y":0.0,"Z":0.0},"TrackingState":0}},"LeanTrackingState":0,"TrackingId":0}]