[{"Lean":{"X":0.327013075,"Y":0.03009776},"Activities":{"EyeLeftClosed":0,"EyeRightClosed":0,"MouthOpen":0,"MouthMoved":0,"LookingAway":0},"Appearance":{"WearingGlasses":0},"ClippedEdges":0,"Engaged":0,"Expressions":{"Neutral":0,"Happy":0},"HandLeftConfidence":0,"HandLeftState":0,"HandRightConfidence":0,"HandRightState":0,"IsRestricted":false,"IsTracked":true,"JointOrientations":{"SpineBase":{"JointType":0,"Orientation":{"X":0.0590384156,"Y":0.99699986,"Z":-0.010347737,"W":-0.0489770919}},"SpineMid":{"JointType":1,"Orientation":{"X":0.05899278,"Y":0.9972037,"Z":-0.01060482,"W":-0.04463353}},"Neck":{"JointType":2,"Orientation":{"X":0.0494076647,"Y":0.9967385,"Z":-0.0476862863,"W":-0.0423961654}},"Head":{"JointType":3,"Orientation":{"X":0.0,"Y":0.0,"Z":0.0,"W":0.0}},"ShoulderLeft":{"JointType":4,"Orientation":{"X":0.8020191,"Y":-0.5971776,"Z":0.00532804057,"W":0.0107604694}},"ElbowLeft":{"JointType":5,"Orientation":{"X":-0.547025561,"Y":0.6050507,"Z":0.5665674,"W":0.11695344}},"WristLeft":{"JointType":6,"Orientation":{"X":0.7484869,"Y":-0.4970632,"Z":-0.407010049,"W":-0.164433688}},"HandLeft":{"JointType":7,"Orientation":{"X":0.8053339,"Y":-0.404750228,"Z":-0.309993684,"W":-0.302520216}},"ShoulderRight":{"JointType":8,"Orientation":{"X":0.850962937,"Y":0.51881963,"Z":-0.07052217,"W":-0.0414117761}},"ElbowRight":{"JointType":9,"Orientation":{"X":0.762944,"Y":0.376309752,"Z":0.5230518,"W":-0.0521956235}},"WristRight":{"JointType":10,"Orientation":{"X":0.9364825,"Y":0.2857471,"Z":-0.16933316,"W":0.112585127}},"HandRight":{"JointType":11,"Orientation":{"X":0.8980033,"Y":0.284484565,"Z":-0.255983919,"W":-0.217096388}},"HipLeft":{"JointType":12,"Orientation":{"X":-0.69251436,"Y":0.698523343,"Z":-0.148688167,"W":0.101886116}},"KneeLeft":{"JointType":13,"Orientation":{"X":-0.394502878,"Y":-0.170242563,"Z":0.6822539,"W":0.5915357}},"AnkleLeft":{"JointType":14,"Orientation":{"X":-0.5905546,"Y":0.09489108,"Z":0.793990135,"W":0.108723268}},"FootLeft":{"JointType":15,"Orientation":{"X":0.0,"Y":0.0,"Z":0.0,"W":0.0}},"HipRight":{"JointType":16,"Orientation":{"X":0.702158451,"Y":0.651841342,"Z":-0.1942579,"W":-0.210570931}},"KneeRight":{"JointType":17,"Orientation":{"X":0.740542233,"Y":-0.0128252367,"Z":0.6689805,"W":0.0624325275}},"AnkleRight":{"JointType":18,"Orientation":{"X":0.7357596,"Y":0.0302574635,"Z":0.672037,"W":0.07815803}},"FootRight":{"JointType":19,"Orientation":{"X":0.0,"Y":0.0,"Z":0.0,"W":0.0}},"SpineShoulder":{"JointType":20,"Orientation":{"X":0.0534919053,"Y":0.9973503,"Z":-0.027097892,"W":-0.0411912948}},"HandTipLeft":{"JointType":21,"Orientation":{"X":0.0,"Y":0.0,"Z":0.0,"W":0.0}},"ThumbLeft":{"JointType":22,"Orientation":{"X":0.0,"Y":0.0,"Z":0.0,"W":0.0}},"HandTipRight":{"JointType":23,"Orientation":{"X":0.0,"Y":0.0,"Z":0.0,"W":0.0}},"ThumbRight":{"JointType":24,"Orientation":{"X":0.0,"Y":0.0,"Z":0.0,"W":0.0}}},"Joints":{"SpineBase":{"JointType":0,"Position":{"X":0.371497124,"Y":0.154572234,"Z":2.19805479},"TrackingState":2},"SpineMid":{"JointType":1,"Position":{"X":0.408759147,"Y":0.47155118,"Z":2.18962073},"TrackingState":2},"Neck":{"JointType":2,"Position":{"X":0.440047055,"Y":0.775867939,"Z":2.16863251},"TrackingState":2},"Head":{"JointType":3,"Position":{"X":0.47362265,"Y":0.9455598,"Z":2.15615988},"TrackingState":2},"ShoulderLeft":{"JointType":4,"Position":{"X":0.307237417,"Y":0.663971663,"Z":2.17750645},"TrackingState":2},"ElbowLeft":{"JointType":5,"Position":{"X":0.0867317,"Y":0.5972296,"Z":2.33228087},"TrackingState":2},"WristLeft":{"JointType":6,"Position":{"X":-0.119518422,"Y":0.4910956,"Z":2.3695085},"TrackingState":2},"HandLeft":{"JointType":7,"Position":{"X":-0.212980047,"Y":0.436618328,"Z":2.3431983},"TrackingState":2},"ShoulderRight":{"JointType":8,"Position":{"X":0.5772364,"Y":0.6262063,"Z":2.152448},"TrackingState":2},"ElbowRight":{"JointType":9,"Position":{"X":0.728895664,"Y":0.454643279,"Z":2.22818351},"TrackingState":2},"WristRight":{"JointType":10,"Position":{"X":0.8626608,"Y":0.2653436,"Z":2.25480366},"TrackingState":2},"HandRight":{"JointType":11,"Position":{"X":0.872826457,"Y":0.246428758,"Z":2.241186},"TrackingState":2},"HipLeft":{"JointType":12,"Position":{"X":0.287231,"Y":0.154269338,"Z":2.166689},"TrackingState":2},"KneeLeft":{"JointType":13,"Position":{"X":0.0182417538,"Y":0.05743878,"Z":1.88722944},"TrackingState":2},"AnkleLeft":{"JointType":14,"Position":{"X":-0.09004304,"Y":-0.307032019,"Z":1.89569938},"TrackingState":2},"FootLeft":{"JointType":15,"Position":{"X":-0.140033871,"Y":-0.380913526,"Z":1.80701506},"TrackingState":2},"HipRight":{"JointType":16,"Position":{"X":0.442487478,"Y":0.149332538,"Z":2.15130377},"TrackingState":2},"KneeRight":{"JointType":17,"Position":{"X":0.4025691,"Y":-0.236847267,"Z":2.18062449},"TrackingState":2},"AnkleRight":{"JointType":18,"Position":{"X":0.379407853,"Y":-0.614138961,"Z":2.240198},"TrackingState":2},"FootRight":{"JointType":19,"Position":{"X":0.366185665,"Y":-0.6466162,"Z":2.113313},"TrackingState":2},"SpineShoulder":{"JointType":20,"Position":{"X":0.432963252,"Y":0.7015743,"Z":2.17607641},"TrackingState":2},"HandTipLeft":{"JointType":21,"Position":{"X":-0.275331318,"Y":0.362380356,"Z":2.34406662},"TrackingState":2},"ThumbLeft":{"JointType":22,"Position":{"X":-0.245241791,"Y":0.429165661,"Z":2.30523372},"TrackingState":2},"HandTipRight":{"JointType":23,"Position":{"X":0.9223534,"Y":0.125087589,"Z":2.189291},"TrackingState":2},"ThumbRight":{"JointType":24,"Position":{"X":0.916166,"Y":0.125180438,"Z":2.17643452},"TrackingState":2}},"LeanTrackingState":2,"TrackingId":72057594037929101},{"Lean":{"X":0.0,"Y":0.0},"Activities":{"EyeLeftClosed":0,"EyeRightClosed":0,"MouthOpen":0,"MouthMoved":0,"LookingAway":0},"Appearance":{"WearingGlasses":0},"ClippedEdges":0,"Engaged":0,"Expressions":{"Neutral":0,"Happy":0},"HandLeftConfidence":1,"HandLeftState":1,"HandRightConfidence":1,"HandRightState":1,"IsRestricted":false,"IsTracked":false,"JointOrientations":{"SpineBase":{"JointType":0,"Orientation":{"X":0.0,"Y":0.0,"Z":0.0,"W":0.0}},"SpineMid":{"JointType":1,"Orientation":{"X":0.0,"Y":0.0,"Z":0.0,"W":0.0}},"Neck":{"JointType":2,"Orientation":{"X":0.0,"Y":0.0,"Z":0.0,"W":0.0}},"Head":{"JointType":3,"Orientation":{"X":0.0,"Y":0.0,"Z":0.0,"W":0.0}},"ShoulderLeft":{"JointType":4,"Orientation":{"X":0.0,"Y":0.0,"Z":0.0,"W":0.0}},"ElbowLeft":{"JointType":5,"Orientation":{"X":0.0,"Y":0.0,"Z":0.0,"W":0.0}},"WristLeft":{"JointType":6,"Orientation":{"X":0.0,"Y":0.0,"Z":0.0,"W":0.0}},"HandLeft":{"JointType":7,"Orientation":{"X":0.0,"Y":0.0,"Z":0.0,"W":0.0}},"ShoulderRight":{"JointType":8,"Orientation":{"X":0.0,"Y":0.0,"Z":0.0,"W":0.0}},"ElbowRight":{"JointType":9,"Orientation":{"X":0.0,"Y":0.0,"Z":0.0,"W":0.0}},"WristRight":{"JointType":10,"Orientation":{"X":0.0,"Y":0.0,"Z":0.0,"W":0.0}},"HandRight":{"JointType":11,"Orientation":{"X":0.0,"Y":0.0,"Z":0.0,"W":0.0}},"HipLeft":{"JointType":12,"Orientation":{"X":0.0,"Y":0.0,"Z":0.0,"W":0.0}},"KneeLeft":{"JointType":13,"Orientation":{"X":0.0,"Y":0.0,"Z":0.0,"W":0.0}},"AnkleLeft":{"JointType":14,"Orientation":{"X":0.0,"Y":0.0,"Z":0.0,"W":0.0}},"FootLeft":{"JointType":15,"Orientation":{"X":0.0,"Y":0.0,"Z":0.0,"W":0.0}},"HipRight":{"JointType":16,"Orientation":{"X":0.0,"Y":0.0,"Z":0.0,"W":0.0}},"KneeRight":{"JointType":17,"Orientation":{"X":0.0,"Y":0.0,"Z":0.0,"W":0.0}},"AnkleRight":{"JointType":18,"Orientation":{"X":0.0,"Y":0.0,"Z":0.0,"W":0.0}},"FootRight":{"JointType":19,"Orientation":{"X":0.0,"Y":0.0,"Z":0.0,"W":0.0}},"SpineShoulder":{"JointType":20,"Orientation":{"X":0.0,"Y":0.0,"Z":0.0,"W":0.0}},"HandTipLeft":{"JointType":21,"Orientation":{"X":0.0,"Y":0.0,"Z":0.0,"W":0.0}},"ThumbLeft":{"JointType":22,"Orientation":{"X":0.0,"Y":0.0,"Z":0.0,"W":0.0}},"HandTipRight":{"JointType":23,"Orientation":{"X":0.0,"Y":0.0,"Z":0.0,"W":0.0}},"ThumbRight":{"JointType":24,"Orientation":{"X":0.0,"Y":0.0,"Z":0.0,"W":0.0}}},"Joints":{"SpineBase":{"JointType":0,"Position":{"X":0.0,"Y":0.0,"Z":0.0},"TrackingState":0},"SpineMid":{"JointType":1,"Position":{"X":0.0,"Y":0.0,"Z":0.0},"TrackingState":0},"Neck":{"JointType":2,"Position":{"X":0.0,"Y":0.0,"Z":0.0},"TrackingState":0},"Head":{"JointType":3,"Position":{"X":0.0,"Y":0.0,"Z":0.0},"TrackingState":0},"ShoulderLeft":{"JointType":4,"Position":{"X":0.0,"Y":0.0,"Z":0.0},"TrackingState":0},"ElbowLeft":{"JointType":5,"Position":{"X":0.0,"Y":0.0,"Z":0.0},"TrackingState":0},"WristLeft":{"JointType":6,"Position":{"X":0.0,"Y":0.0,"Z":0.0},"TrackingState":0},"HandLeft":{"JointType":7,"Position":{"X":0.0,"Y":0.0,"Z":0.0},"TrackingState":0},"ShoulderRight":{"JointType":8,"Position":{"X":0.0,"Y":0.0,"Z":0.0},"TrackingState":0},"ElbowRight":{"JointType":9,"Position":{"X":0.0,"Y":0.0,"Z":0.0},"TrackingState":0},"WristRight":{"JointType":10,"Position":{"X":0.0,"Y":0.0,"Z":0.0},"TrackingState":0},"HandRight":{"JointType":11,"Position":{"X":0.0,"Y":0.0,"Z":0.0},"TrackingState":0},"HipLeft":{"JointType":12,"Position":{"X":0.0,"Y":0.0,"Z":0.0},"TrackingState":0},"KneeLeft":{"JointType":13,"Position":{"X":0.0,"Y":0.0,"Z":0.0},"TrackingState":0},"AnkleLeft":{"JointType":14,"Position":{"X":0.0,"Y":0.0,"Z":0.0},"TrackingState":0},"FootLeft":{"JointType":15,"Position":{"X":0.0,"Y":0.0,"Z":0.0},"TrackingState":0},"HipRight":{"JointType":16,"Position":{"X":0.0,"Y":0.0,"Z":0.0},"TrackingState":0},"KneeRight":{"JointType":17,"Position":{"X":0.0,"Y":0.0,"Z":0.0},"TrackingState":0},"AnkleRight":{"JointType":18,"Position":{"X":0.0,"Y":0.0,"Z":0.0},"TrackingState":0},"FootRight":{"JointType":19,"Position":{"X":0.0,"Y":0.0,"Z":0.0},"TrackingState":0},"SpineShoulder":{"JointType":20,"Position":{"X":0.0,"Y":0.0,"Z":0.0},"TrackingState":0},"HandTipLeft":{"JointType":21,"Position":{"X":0.0,"Y":0.0,"Z":0.0},"TrackingState":0},"ThumbLeft":{"JointType":22,"Position":{"X":0.0,"Y":0.0,"Z":0.0},"TrackingState":0},"HandTipRight":{"JointType":23,"Position":{"X":0.0,"Y":0.0,"Z":0.0},"TrackingState":0},"ThumbRight":{"JointType":24,"Position":{"X":0.0,"Y":0.0,"Z":0.0},"TrackingState":0}},"LeanTrackingState":0,"TrackingId":0},{"Lean":{"X":0.0,"Y":0.0},"Activities":{"EyeLeftClosed":0,"EyeRightClosed":0,"MouthOpen":0,"MouthMoved":0,"LookingAway":0},"Appearance":{"WearingGlasses":0},"ClippedEdges":0,"Engaged":0,"Expressions":{"Neutral":0,"Happy":0},"HandLeftConfidence":1,"HandLeftState":1,"HandRightConfidence":1,"HandRightState":1,"IsRestricted":false,"IsTracked":false,"JointOrientations":{"SpineBase":{"JointType":0,"Orientation":{"X":0.0,"Y":0.0,"Z":0.0,"W":0.0}},"SpineMid":{"JointType":1,"Orientation":{"X":0.0,"Y":0.0,"Z":0.0,"W":0.0}},"Neck":{"JointType":2,"Orientation":{"X":0.0,"Y":0.0,"Z":0.0,"W":0.0}},"Head":{"JointType":3,"Orientation":{"X":0.0,"Y":0.0,"Z":0.0,"W":0.0}},"ShoulderLeft":{"JointType":4,"Orientation":{"X":0.0,"Y":0.0,"Z":0.0,"W":0.0}},"ElbowLeft":{"JointType":5,"Orientation":{"X":0.0,"Y":0.0,"Z":0.0,"W":0.0}},"WristLeft":{"JointType":6,"Orientation":{"X":0.0,"Y":0.0,"Z":0.0,"W":0.0}},"HandLeft":{"JointType":7,"Orientation":{"X":0.0,"Y":0.0,"Z":0.0,"W":0.0}},"ShoulderRight":{"JointType":8,"Orientation":{"X":0.0,"Y":0.0,"Z":0.0,"W":0.0}},"ElbowRight":{"JointType":9,"Orientation":{"X":0.0,"Y":0.0,"Z":0.0,"W":0.0}},"WristRight":{"JointType":10,"Orientation":{"X":0.0,"Y":0.0,"Z":0.0,"W":0.0}},"HandRight":{"JointType":11,"Orientation":{"X":0.0,"Y":0.0,"Z":0.0,"W":0.0}},"HipLeft":{"JointType":12,"Orientation":{"X":0.0,"Y":0.0,"Z":0.0,"W":0.0}},"KneeLeft":{"JointType":13,"Orientation":{"X":0.0,"Y":0.0,"Z":0.0,"W":0.0}},"AnkleLeft":{"JointType":14,"Orientation":{"X":0.0,"Y":0.0,"Z":0.0,"W":0.0}},"FootLeft":{"JointType":15,"Orientation":{"X":0.0,"Y":0.0,"Z":0.0,"W":0.0}},"HipRight":{"JointType":16,"Orientation":{"X":0.0,"Y":0.0,"Z":0.0,"W":0.0}},"KneeRight":{"JointType":17,"Orientation":{"X":0.0,"Y":0.0,"Z":0.0,"W":0.0}},"AnkleRight":{"JointType":18,"Orientation":{"X":0.0,"Y":0.0,"Z":0.0,"W":0.0}},"FootRight":{"JointType":19,"Orientation":{"X":0.0,"Y":0.0,"Z":0.0,"W":0.0}},"SpineShoulder":{"JointType":20,"Orientation":{"X":0.0,"Y":0.0,"Z":0.0,"W":0.0}},"HandTipLeft":{"JointType":21,"Orientation":{"X":0.0,"Y":0.0,"Z":0.0,"W":0.0}},"ThumbLeft":{"JointType":22,"Orientation":{"X":0.0,"Y":0.0,"Z":0.0,"W":0.0}},"HandTipRight":{"JointType":23,"Orientation":{"X":0.0,"Y":0.0,"Z":0.0,"W":0.0}},"ThumbRight":{"JointType":24,"Orientation":{"X":0.0,"Y":0.0,"Z":0.0,"W":0.0}}},"Joints":{"SpineBase":{"JointType":0,"Position":{"X":0.0,"Y":0.0,"Z":0.0},"TrackingState":0},"SpineMid":{"JointType":1,"Position":{"X":0.0,"Y":0.0,"Z":0.0},"TrackingState":0},"Neck":{"JointType":2,"Position":{"X":0.0,"Y":0.0,"Z":0.0},"TrackingState":0},"Head":{"JointType":3,"Position":{"X":0.0,"Y":0.0,"Z":0.0},"TrackingState":0},"ShoulderLeft":{"JointType":4,"Position":{"X":0.0,"Y":0.0,"Z":0.0},"TrackingState":0},"ElbowLeft":{"JointType":5,"Position":{"X":0.0,"Y":0.0,"Z":0.0},"TrackingState":0},"WristLeft":{"JointType":6,"Position":{"X":0.0,"Y":0.0,"Z":0.0},"TrackingState":0},"HandLeft":{"JointType":7,"Position":{"X":0.0,"Y":0.0,"Z":0.0},"TrackingState":0},"ShoulderRight":{"JointType":8,"Position":{"X":0.0,"Y":0.0,"Z":0.0},"TrackingState":0},"ElbowRight":{"JointType":9,"Position":{"X":0.0,"Y":0.0,"Z":0.0},"TrackingState":0},"WristRight":{"JointType":10,"Position":{"X":0.0,"Y":0.0,"Z":0.0},"TrackingState":0},"HandRight":{"JointType":11,"Position":{"X":0.0,"Y":0.0,"Z":0.0},"TrackingState":0},"HipLeft":{"JointType":12,"Position":{"X":0.0,"Y":0.0,"Z":0.0},"TrackingState":0},"KneeLeft":{"JointType":13,"Position":{"X":0.0,"Y":0.0,"Z":0.0},"TrackingState":0},"AnkleLeft":{"JointType":14,"Position":{"X":0.0,"Y":0.0,"Z":0.0},"TrackingState":0},"FootLeft":{"JointType":15,"Position":{"X":0.0,"Y":0.0,"Z":0.0},"TrackingState":0},"HipRight":{"JointType":16,"Position":{"X":0.0,"Y":0.0,"Z":0.0},"TrackingState":0},"KneeRight":{"JointType":17,"Position":{"X":0.0,"Y":0.0,"Z":0.0},"TrackingState":0},"AnkleRight":{"JointType":18,"Position":{"X":0.0,"Y":0.0,"Z":0.0},"TrackingState":0},"FootRight":{"JointType":19,"Position":{"X":0.0,"Y":0.0,"Z":0.0},"TrackingState":0},"SpineShoulder":{"JointType":20,"Position":{"X":0.0,"Y":0.0,"Z":0.0},"TrackingState":0},"HandTipLeft":{"JointType":21,"Position":{"X":0.0,"Y":0.0,"Z":0.0},"TrackingState":0},"ThumbLeft":{"JointType":22,"Position":{"X":0.0,"Y":0.0,"Z":0.0},"TrackingState":0},"HandTipRight":{"JointType":23,"Position":{"X":0.0,"Y":0.0,"Z":0.0},"TrackingState":0},"ThumbRight":{"JointType":24,"Position":{"X":0.0,"Y":0.0,"Z":0.0},"TrackingState":0}},"LeanTrackingState":0,"TrackingId":0},{"Lean":{"X":0.0,"Y":0.0},"Activities":{"EyeLeftClosed":0,"EyeRightClosed":0,"MouthOpen":0,"MouthMoved":0,"LookingAway":0},"Appearance":{"WearingGlasses":0},"ClippedEdges":0,"Engaged":0,"Expressions":{"Neutral":0,"Happy":0},"HandLeftConfidence":1,"HandLeftState":1,"HandRightConfidence":1,"HandRightState":1,"IsRestricted":false,"IsTracked":false,"JointOrientations":{"SpineBase":{"JointType":0,"Orientation":{"X":0.0,"Y":0.0,"Z":0.0,"W":0.0}},"SpineMid":{"JointType":1,"Orientation":{"X":0.0,"Y":0.0,"Z":0.0,"W":0.0}},"Neck":{"JointType":2,"Orientation":{"X":0.0,"Y":0.0,"Z":0.0,"W":0.0}},"Head":{"JointType":3,"Orientation":{"X":0.0,"Y":0.0,"Z":0.0,"W":0.0}},"ShoulderLeft":{"JointType":4,"Orientation":{"X":0.0,"Y":0.0,"Z":0.0,"W":0.0}},"ElbowLeft":{"JointType":5,"Orientation":{"X":0.0,"Y":0.0,"Z":0.0,"W":0.0}},"WristLeft":{"JointType":6,"Orientation":{"X":0.0,"Y":0.0,"Z":0.0,"W":0.0}},"HandLeft":{"JointType":7,"Orientation":{"X":0.0,"Y":0.0,"Z":0.0,"W":0.0}},"ShoulderRight":{"JointType":8,"Orientation":{"X":0.0,"Y":0.0,"Z":0.0,"W":0.0}},"ElbowRight":{"JointType":9,"Orientation":{"X":0.0,"Y":0.0,"Z":0.0,"W":0.0}},"WristRight":{"JointType":10,"Orientation":{"X":0.0,"Y":0.0,"Z":0.0,"W":0.0}},"HandRight":{"JointType":11,"Orientation":{"X":0.0,"Y":0.0,"Z":0.0,"W":0.0}},"HipLeft":{"JointType":12,"Orientation":{"X":0.0,"Y":0.0,"Z":0.0,"W":0.0}},"KneeLeft":{"JointType":13,"Orientation":{"X":0.0,"Y":0.0,"Z":0.0,"W":0.0}},"AnkleLeft":{"JointType":14,"Orientation":{"X":0.0,"Y":0.0,"Z":0.0,"W":0.0}},"FootLeft":{"JointType":15,"Orientation":{"X":0.0,"Y":0.0,"Z":0.0,"W":0.0}},"HipRight":{"JointType":16,"Orientation":{"X":0.0,"Y":0.0,"Z":0.0,"W":0.0}},"KneeRight":{"JointType":17,"Orientation":{"X":0.0,"Y":0.0,"Z":0.0,"W":0.0}},"AnkleRight":{"JointType":18,"Orientation":{"X":0.0,"Y":0.0,"Z":0.0,"W":0.0}},"FootRight":{"JointType":19,"Orientation":{"X":0.0,"Y":0.0,"Z":0.0,"W":0.0}},"SpineShoulder":{"JointType":20,"Orientation":{"X":0.0,"Y":0.0,"Z":0.0,"W":0.0}},"HandTipLeft":{"JointType":21,"Orientation":{"X":0.0,"Y":0.0,"Z":0.0,"W":0.0}},"ThumbLeft":{"JointType":22,"Orientation":{"X":0.0,"Y":0.0,"Z":0.0,"W":0.0}},"HandTipRight":{"JointType":23,"Orientation":{"X":0.0,"Y":0.0,"Z":0.0,"W":0.0}},"ThumbRight":{"JointType":24,"Orientation":{"X":0.0,"Y":0.0,"Z":0.0,"W":0.0}}},"Joints":{"SpineBase":{"JointType":0,"Position":{"X":0.0,"Y":0.0,"Z":0.0},"TrackingState":0},"SpineMid":{"JointType":1,"Position":{"X":0.0,"Y":0.0,"Z":0.0},"TrackingState":0},"Neck":{"JointType":2,"Position":{"X":0.0,"Y":0.0,"Z":0.0},"TrackingState":0},"Head":{"JointType":3,"Position":{"X":0.0,"Y":0.0,"Z":0.0},"TrackingState":0},"ShoulderLeft":{"JointType":4,"Position":{"X":0.0,"Y":0.0,"Z":0.0},"TrackingState":0},"ElbowLeft":{"JointType":5,"Position":{"X":0.0,"Y":0.0,"Z":0.0},"TrackingState":0},"WristLeft":{"JointType":6,"Position":{"X":0.0,"Y":0.0,"Z":0.0},"TrackingState":0},"HandLeft":{"JointType":7,"Position":{"X":0.0,"Y":0.0,"Z":0.0},"TrackingState":0},"ShoulderRight":{"JointType":8,"Position":{"X":0.0,"Y":0.0,"Z":0.0},"TrackingState":0},"ElbowRight":{"JointType":9,"Position":{"X":0.0,"Y":0.0,"Z":0.0},"TrackingState":0},"WristRight":{"JointType":10,"Position":{"X":0.0,"Y":0.0,"Z":0.0},"TrackingState":0},"HandRight":{"JointType":11,"Position":{"X":0.0,"Y":0.0,"Z":0.0},"TrackingState":0},"HipLeft":{"JointType":12,"Position":{"X":0.0,"Y":0.0,"Z":0.0},"TrackingState":0},"KneeLeft":{"JointType":13,"Position":{"X":0.0,"Y":0.0,"Z":0.0},"TrackingState":0},"AnkleLeft":{"JointType":14,"Position":{"X":0.0,"Y":0.0,"Z":0.0},"TrackingState":0},"FootLeft":{"JointType":15,"Position":{"X":0.0,"Y":0.0,"Z":0.0},"TrackingState":0},"HipRight":{"JointType":16,"Position":{"X":0.0,"Y":0.0,"Z":0.0},"TrackingState":0},"KneeRight":{"JointType":17,"Position":{"X":0.0,"Y":0.0,"Z":0.0},"TrackingState":0},"AnkleRight":{"JointType":18,"Position":{"X":0.0,"Y":0.0,"Z":0.0},"TrackingState":0},"FootRight":{"JointType":19,"Position":{"X":0.0,"Y":0.0,"Z":0.0},"TrackingState":0},"SpineShoulder":{"JointType":20,"Position":{"X":0.0,"Y":0.0,"Z":0.0},"TrackingState":0},"HandTipLeft":{"JointType":21,"Position":{"X":0.0,"Y":0.0,"Z":0.0},"TrackingState":0},"ThumbLeft":{"JointType":22,"Position":{"X":0.0,"Y":0.0,"Z":0.0},"TrackingState":0},"HandTipRight":{"JointType":23,"Position":{"X":0.0,"Y":0.0,"Z":0.0},"TrackingState":0},"ThumbRight":{"JointType":24,"Position":{"X":0.0,"Y":0.0,"Z":0.0},"TrackingState":0}},"LeanTrackingState":0,"TrackingId":0},{"Lean":{"X":0.0,"Y":0.0},"Activities":{"EyeLeftClosed":0,"EyeRightClosed":0,"MouthOpen":0,"MouthMoved":0,"LookingAway":0},"Appearance":{"WearingGlasses":0},"ClippedEdges":0,"Engaged":0,"Expressions":{"Neutral":0,"Happy":0},"HandLeftConfidence":1,"HandLeftState":1,"HandRightConfidence":1,"HandRightState":1,"IsRestricted":false,"IsTracked":false,"JointOrientations":{"SpineBase":{"JointType":0,"Orientation":{"X":0.0,"Y":0.0,"Z":0.0,"W":0.0}},"SpineMid":{"JointType":1,"Orientation":{"X":0.0,"Y":0.0,"Z":0.0,"W":0.0}},"Neck":{"JointType":2,"Orientation":{"X":0.0,"Y":0.0,"Z":0.0,"W":0.0}},"Head":{"JointType":3,"Orientation":{"X":0.0,"Y":0.0,"Z":0.0,"W":0.0}},"ShoulderLeft":{"JointType":4,"Orientation":{"X":0.0,"Y":0.0,"Z":0.0,"W":0.0}},"ElbowLeft":{"JointType":5,"Orientation":{"X":0.0,"Y":0.0,"Z":0.0,"W":0.0}},"WristLeft":{"JointType":6,"Orientation":{"X":0.0,"Y":0.0,"Z":0.0,"W":0.0}},"HandLeft":{"JointType":7,"Orientation":{"X":0.0,"Y":0.0,"Z":0.0,"W":0.0}},"ShoulderRight":{"JointType":8,"Orientation":{"X":0.0,"Y":0.0,"Z":0.0,"W":0.0}},"ElbowRight":{"JointType":9,"Orientation":{"X":0.0,"Y":0.0,"Z":0.0,"W":0.0}},"WristRight":{"JointType":10,"Orientation":{"X":0.0,"Y":0.0,"Z":0.0,"W":0.0}},"HandRight":{"JointType":11,"Orientation":{"X":0.0,"Y":0.0,"Z":0.0,"W":0.0}},"HipLeft":{"JointType":12,"Orientation":{"X":0.0,"Y":0.0,"Z":0.0,"W":0.0}},"KneeLeft":{"JointType":13,"Orientation":{"X":0.0,"Y":0.0,"Z":0.0,"W":0.0}},"AnkleLeft":{"JointType":14,"Orientation":{"X":0.0,"Y":0.0,"Z":0.0,"W":0.0}},"FootLeft":{"JointType":15,"Orientation":{"X":0.0,"Y":0.0,"Z":0.0,"W":0.0}},"HipRight":{"JointType":16,"Orientation":{"X":0.0,"Y":0.0,"Z":0.0,"W":0.0}},"KneeRight":{"JointType":17,"Orientation":{"X":0.0,"Y":0.0,"Z":0.0,"W":0.0}},"AnkleRight":{"JointType":18,"Orientation":{"X":0.0,"Y":0.0,"Z":0.0,"W":0.0}},"FootRight":{"JointType":19,"Orientation":{"X":0.0,"Y":0.0,"Z":0.0,"W":0.0}},"SpineShoulder":{"JointType":20,"Orientation":{"X":0.0,"Y":0.0,"Z":0.0,"W":0.0}},"HandTipLeft":{"JointType":21,"Orientation":{"X":0.0,"Y":0.0,"Z":0.0,"W":0.0}},"ThumbLeft":{"JointType":22,"Orientation":{"X":0.0,"Y":0.0,"Z":0.0,"W":0.0}},"HandTipRight":{"JointType":23,"Orientation":{"X":0.0,"Y":0.0,"Z":0.0,"W":0.0}},"ThumbRight":{"JointType":24,"Orientation":{"X":0.0,"Y":0.0,"Z":0.0,"W":0.0}}},"Joints":{"SpineBase":{"JointType":0,"Position":{"X":0.0,"Y":0.0,"Z":0.0},"TrackingState":0},"SpineMid":{"JointType":1,"Position":{"X":0.0,"Y":0.0,"Z":0.0},"TrackingState":0},"Neck":{"JointType":2,"Position":{"X":0.0,"Y":0.0,"Z":0.0},"TrackingState":0},"Head":{"JointType":3,"Position":{"X":0.0,"Y":0.0,"Z":0.0},"TrackingState":0},"ShoulderLeft":{"JointType":4,"Position":{"X":0.0,"Y":0.0,"Z":0.0},"TrackingState":0},"ElbowLeft":{"JointType":5,"Position":{"X":0.0,"Y":0.0,"Z":0.0},"TrackingState":0},"WristLeft":{"JointType":6,"Position":{"X":0.0,"Y":0.0,"Z":0.0},"TrackingState":0},"HandLeft":{"JointType":7,"Position":{"X":0.0,"Y":0.0,"Z":0.0},"TrackingState":0},"ShoulderRight":{"JointType":8,"Position":{"X":0.0,"Y":0.0,"Z":0.0},"TrackingState":0},"ElbowRight":{"JointType":9,"Position":{"X":0.0,"Y":0.0,"Z":0.0},"TrackingState":0},"WristRight":{"JointType":10,"Position":{"X":0.0,"Y":0.0,"Z":0.0},"TrackingState":0},"HandRight":{"JointType":11,"Position":{"X":0.0,"Y":0.0,"Z":0.0},"TrackingState":0},"HipLeft":{"JointType":12,"Position":{"X":0.0,"Y":0.0,"Z":0.0},"TrackingState":0},"KneeLeft":{"JointType":13,"Position":{"X":0.0,"Y":0.0,"Z":0.0},"TrackingState":0},"AnkleLeft":{"JointType":14,"Position":{"X":0.0,"Y":0.0,"Z":0.0},"TrackingState":0},"FootLeft":{"JointType":15,"Position":{"X":0.0,"Y":0.0,"Z":0.0},"TrackingState":0},"HipRight":{"JointType":16,"Position":{"X":0.0,"Y":0.0,"Z":0.0},"TrackingState":0},"KneeRight":{"JointType":17,"Position":{"X":0.0,"Y":0.0,"Z":0.0},"TrackingState":0},"AnkleRight":{"JointType":18,"Position":{"X":0.0,"Y":0.0,"Z":0.0},"TrackingState":0},"FootRight":{"JointType":19,"Position":{"X":0.0,"Y":0.0,"Z":0.0},"TrackingState":0},"SpineShoulder":{"JointType":20,"Position":{"X":0.0,"Y":0.0,"Z":0.0},"TrackingState":0},"HandTipLeft":{"JointType":21,"Position":{"X":0.0,"Y":0.0,"Z":0.0},"TrackingState":0},"ThumbLeft":{"JointType":22,"Position":{"X":0.0,"Y":0.0,"Z":0.0},"TrackingState":0},"HandTipRight":{"JointType":23,"Position":{"X":0.0,"Y":0.0,"Z":0.0},"TrackingState":0},"ThumbRight":{"JointType":24,"Position":{"X":0.0,"Y":0.0,"Z":0.0},"TrackingState":0}},"LeanTrackingState":0,"TrackingId":0},{"Lean":{"X":0.0,"Y":0.0},"Activities":{"EyeLeftClosed":0,"EyeRightClosed":0,"MouthOpen":0,"MouthMoved":0,"LookingAway":0},"Appearance":{"WearingGlasses":0},"ClippedEdges":0,"Engaged":0,"Expressions":{"Neutral":0,"Happy":0},"HandLeftConfidence":1,"HandLeftState":1,"HandRightConfidence":1,"HandRightState":1,"IsRestricted":false,"IsTracked":false,"JointOrientations":{"SpineBase":{"JointType":0,"Orientation":{"X":0.0,"Y":0.0,"Z":0.0,"W":0.0}},"SpineMid":{"JointType":1,"Orientation":{"X":0.0,"Y":0.0,"Z":0.0,"W":0.0}},"Neck":{"JointType":2,"Orientation":{"X":0.0,"Y":0.0,"Z":0.0,"W":0.0}},"Head":{"JointType":3,"Orientation":{"X":0.0,"Y":0.0,"Z":0.0,"W":0.0}},"ShoulderLeft":{"JointType":4,"Orientation":{"X":0.0,"Y":0.0,"Z":0.0,"W":0.0}},"ElbowLeft":{"JointType":5,"Orientation":{"X":0.0,"Y":0.0,"Z":0.0,"W":0.0}},"WristLeft":{"JointType":6,"Orientation":{"X":0.0,"Y":0.0,"Z":0.0,"W":0.0}},"HandLeft":{"JointType":7,"Orientation":{"X":0.0,"Y":0.0,"Z":0.0,"W":0.0}},"ShoulderRight":{"JointType":8,"Orientation":{"X":0.0,"Y":0.0,"Z":0.0,"W":0.0}},"ElbowRight":{"JointType":9,"Orientation":{"X":0.0,"Y":0.0,"Z":0.0,"W":0.0}},"WristRight":{"JointType":10,"Orientation":{"X":0.0,"Y":0.0,"Z":0.0,"W":0.0}},"HandRight":{"JointType":11,"Orientation":{"X":0.0,"Y":0.0,"Z":0.0,"W":0.0}},"HipLeft":{"JointType":12,"Orientation":{"X":0.0,"Y":0.0,"Z":0.0,"W":0.0}},"KneeLeft":{"JointType":13,"Orientation":{"X":0.0,"Y":0.0,"Z":0.0,"W":0.0}},"AnkleLeft":{"JointType":14,"Orientation":{"X":0.0,"Y":0.0,"Z":0.0,"W":0.0}},"FootLeft":{"JointType":15,"Orientation":{"X":0.0,"Y":0.0,"Z":0.0,"W":0.0}},"HipRight":{"JointType":16,"Orientation":{"X":0.0,"Y":0.0,"Z":0.0,"W":0.0}},"KneeRight":{"JointType":17,"Orientation":{"X":0.0,"Y":0.0,"Z":0.0,"W":0.0}},"AnkleRight":{"JointType":18,"Orientation":{"X":0.0,"Y":0.0,"Z":0.0,"W":0.0}},"FootRight":{"JointType":19,"Orientation":{"X":0.0,"Y":0.0,"Z":0.0,"W":0.0}},"SpineShoulder":{"JointType":20,"Orientation":{"X":0.0,"Y":0.0,"Z":0.0,"W":0.0}},"HandTipLeft":{"JointType":21,"Orientation":{"X":0.0,"Y":0.0,"Z":0.0,"W":0.0}},"ThumbLeft":{"JointType":22,"Orientation":{"X":0.0,"Y":0.0,"Z":0.0,"W":0.0}},"HandTipRight":{"JointType":23,"Orientation":{"X":0.0,"Y":0.0,"Z":0.0,"W":0.0}},"ThumbRight":{"JointType":24,"Orientation":{"X":0.0,"Y":0.0,"Z":0.0,"W":0.0}}},"Joints":{"SpineBase":{"JointType":0,"Position":{"X":0.0,"Y":0.0,"Z":0.0},"TrackingState":0},"SpineMid":{"JointType":1,"Position":{"X":0.0,"Y":0.0,"Z":0.0},"TrackingState":0},"Neck":{"JointType":2,"Position":{"X":0.0,"Y":0.0,"Z":0.0},"TrackingState":0},"Head":{"JointType":3,"Position":{"X":0.0,"Y":0.0,"Z":0.0},"TrackingState":0},"ShoulderLeft":{"JointType":4,"Position":{"X":0.0,"Y":0.0,"Z":0.0},"TrackingState":0},"ElbowLeft":{"JointType":5,"Position":{"X":0.0,"Y":0.0,"Z":0.0},"TrackingState":0},"WristLeft":{"JointType":6,"Position":{"X":0.0,"Y":0.0,"Z":0.0},"TrackingState":0},"HandLeft":{"JointType":7,"Position":{"X":0.0,"Y":0.0,"Z":0.0},"TrackingState":0},"ShoulderRight":{"JointType":8,"Position":{"X":0.0,"Y":0.0,"Z":0.0},"TrackingState":0},"ElbowRight":{"JointType":9,"Position":{"X":0.0,"Y":0.0,"Z":0.0},"TrackingState":0},"WristRight":{"JointType":10,"Position":{"X":0.0,"Y":0.0,"Z":0.0},"TrackingState":0},"HandRight":{"JointType":11,"Position":{"X":0.0,"Y":0.0,"Z":0.0},"TrackingState":0},"HipLeft":{"JointType":12,"Position":{"X":0.0,"Y":0.0,"Z":0.0},"TrackingState":0},"KneeLeft":{"JointType":13,"Position":{"X":0.0,"Y":0.0,"Z":0.0},"TrackingState":0},"AnkleLeft":{"JointType":14,"Position":{"X":0.0,"Y":0.0,"Z":0.0},"TrackingState":0},"FootLeft":{"JointType":15,"Position":{"X":0.0,"Y":0.0,"Z":0.0},"TrackingState":0},"HipRight":{"JointType":16,"Position":{"X":0.0,"Y":0.0,"Z":0.0},"TrackingState":0},"KneeRight":{"JointType":17,"Position":{"X":0.0,"Y":0.0,"Z":0.0},"TrackingState":0},"AnkleRight":{"JointType":18,"Position":{"X":0.0,"Y":0.0,"Z":0.0},"TrackingState":0},"FootRight":{"JointType":19,"Position":{"X":0.0,"Y":0.0,"Z":0.0},"TrackingState":0},"SpineShoulder":{"JointType":20,"Position":{"X":0.0,"Y":0.0,"Z":0.0},"TrackingState":0},"HandTipLeft":{"JointType":21,"Position":{"X":0.0,"Y":0.0,"Z":0.0},"TrackingState":0},"ThumbLeft":{"JointType":22,"Position":{"X":0.0,"Y":0.0,"Z":0.0},"TrackingState":0},"HandTipRight":{"JointType":23,"Position":{"X":0.0,"Y":0.0,"Z":0.0},"TrackingState":0},"ThumbRight":{"JointType":24,"Position":{"X":0.0,"Y":0.0,"Z":0.0},"TrackingState":0}},"LeanTrackingState":0,"TrackingId":0}]